faucet_extractor_poc/__init__.py
faucet_extractor_poc/extract.py
faucet_extractor_poc/discord/__init__.py
faucet_extractor_poc/discord/webhook.py
faucet_extractor_poc/faucets/__init__.py
faucet_extractor_poc/faucets/base.py
faucet_extractor_poc/faucets/bera.py
faucet_extractor_poc/faucets/monad.py
faucet_extractor_poc/utils/__init__.py
faucet_extractor_poc/utils/logger.py
faucet_extractor_poc/utils/validation.py
faucet_extractor_poc-1.4.0.dist-info/licenses/LICENSE
faucet_extractor_poc-1.4.0.dist-info/METADATA
faucet_extractor_poc-1.4.0.dist-info/WHEEL
faucet_extractor_poc-1.4.0.dist-info/entry_points.txt
faucet_extractor_poc-1.4.0.dist-info/top_level.txt
faucet_extractor_poc-1.4.0.dist-info/RECORD
