Metadata-Version: 2.4
Name: faucet-extractor-poc
Version: 1.4.0
Summary: Testnet faucet extractor (Proof of Concept)
Home-page: https://github.com/niagarafinance/faucet-extractor-poc
Author: Niagara Finance
Author-email: niagarafinance@proton.me
Keywords: testnet,faucet,ethereum,erc20,web3
Classifier: License :: Other/Proprietary License
Classifier: Operating System :: OS Independent
Classifier: Programming Language :: Python :: 3
Requires-Python: >=3.10
License-File: LICENSE
Requires-Dist: python-dotenv
Requires-Dist: requests
Dynamic: author
Dynamic: author-email
Dynamic: classifier
Dynamic: description
Dynamic: description-content-type
Dynamic: home-page
Dynamic: keywords
Dynamic: license-file
Dynamic: requires-dist
Dynamic: requires-python
Dynamic: summary
